{
  "item": [
    {
      "id": "e96e878a-9e39-4f65-a6c1-8fe5566d068a",
      "name": "commands",
      "item": [
        {
          "id": "6fbed105-d264-49d3-92ac-494b12d727d4",
          "name": "/commands/ChangeRegistrationDetails - POST",
          "request": {
            "name": "/commands/ChangeRegistrationDetails - POST",
            "description": {},
            "url": {
              "path": [
                "commands",
                "ChangeRegistrationDetails"
              ],
              "host": [
                "{{baseUrl}}"
              ],
              "query": [],
              "variable": []
            },
            "header": [
              {
                "key": "Content-Type",
                "value": "application/json"
              }
            ],
            "method": "POST",
            "auth": null,
            "body": {
              "mode": "raw",
              "raw": "{\n    \"id\": \"<string>\",\n    \"startUtc\": \"<dateTime>\",\n    \"endUtc\": \"<dateTime>\",\n    \"vehicleRegistrationMark\": \"<string>\",\n    \"fullName\": \"<string>\",\n    \"visitedName\": \"<string>\"\n}"
            }
          },
          "response": [
            {
              "id": "470b9605-132d-418a-b121-7b58598ffc4d",
              "name": "Success",
              "originalRequest": {
                "url": {
                  "path": [
                    "commands",
                    "ChangeRegistrationDetails"
                  ],
                  "host": [
                    "{{baseUrl}}"
                  ],
                  "query": [],
                  "variable": []
                },
                "method": "POST",
                "body": {
                  "mode": "raw",
                  "raw": "{\n    \"id\": \"<string>\",\n    \"startUtc\": \"<dateTime>\",\n    \"endUtc\": \"<dateTime>\",\n    \"vehicleRegistrationMark\": \"<string>\",\n    \"fullName\": \"<string>\",\n    \"visitedName\": \"<string>\"\n}"
                }
              },
              "status": "Accepted",
              "code": 202,
              "header": [
                {
                  "key": "Content-Type",
                  "value": "text/plain"
                }
              ],
              "body": "",
              "cookie": [],
              "_postman_previewlanguage": "text"
            },
            {
              "id": "ba843cdc-dd32-4fbe-a8b5-4c6421a6fa82",
              "name": "Unauthorized",
              "originalRequest": {
                "url": {
                  "path": [
                    "commands",
                    "ChangeRegistrationDetails"
                  ],
                  "host": [
                    "{{baseUrl}}"
                  ],
                  "query": [],
                  "variable": []
                },
                "method": "POST",
                "body": {
                  "mode": "raw",
                  "raw": "{\n    \"id\": \"<string>\",\n    \"startUtc\": \"<dateTime>\",\n    \"endUtc\": \"<dateTime>\",\n    \"vehicleRegistrationMark\": \"<string>\",\n    \"fullName\": \"<string>\",\n    \"visitedName\": \"<string>\"\n}"
                }
              },
              "status": "Unauthorized",
              "code": 401,
              "header": [
                {
                  "key": "Content-Type",
                  "value": "text/plain"
                }
              ],
              "body": "",
              "cookie": [],
              "_postman_previewlanguage": "text"
            },
            {
              "id": "afa0b7cb-5242-4bd6-b37e-4dd49e877ba2",
              "name": "Forbidden",
              "originalRequest": {
                "url": {
                  "path": [
                    "commands",
                    "ChangeRegistrationDetails"
                  ],
                  "host": [
                    "{{baseUrl}}"
                  ],
                  "query": [],
                  "variable": []
                },
                "method": "POST",
                "body": {
                  "mode": "raw",
                  "raw": "{\n    \"id\": \"<string>\",\n    \"startUtc\": \"<dateTime>\",\n    \"endUtc\": \"<dateTime>\",\n    \"vehicleRegistrationMark\": \"<string>\",\n    \"fullName\": \"<string>\",\n    \"visitedName\": \"<string>\"\n}"
                }
              },
              "status": "Forbidden",
              "code": 403,
              "header": [
                {
                  "key": "Content-Type",
                  "value": "text/plain"
                }
              ],
              "body": "",
              "cookie": [],
              "_postman_previewlanguage": "text"
            },
            {
              "id": "ffe82958-c6b4-45d0-855c-acaf9b4d893c",
              "name": "Too many requests",
              "originalRequest": {
                "url": {
                  "path": [
                    "commands",
                    "ChangeRegistrationDetails"
                  ],
                  "host": [
                    "{{baseUrl}}"
                  ],
                  "query": [],
                  "variable": []
                },
                "method": "POST",
                "body": {
                  "mode": "raw",
                  "raw": "{\n    \"id\": \"<string>\",\n    \"startUtc\": \"<dateTime>\",\n    \"endUtc\": \"<dateTime>\",\n    \"vehicleRegistrationMark\": \"<string>\",\n    \"fullName\": \"<string>\",\n    \"visitedName\": \"<string>\"\n}"
                }
              },
              "status": "Too Many Requests",
              "code": 429,
              "header": [
                {
                  "key": "Content-Type",
                  "value": "text/plain"
                }
              ],
              "body": "",
              "cookie": [],
              "_postman_previewlanguage": "text"
            }
          ],
          "event": []
        },
        {
          "id": "c50e4ad2-d7c3-4021-b960-c73b66c9d53e",
          "name": "/commands/DeleteRegistration - POST",
          "request": {
            "name": "/commands/DeleteRegistration - POST",
            "description": {},
            "url": {
              "path": [
                "commands",
                "DeleteRegistration"
              ],
              "host": [
                "{{baseUrl}}"
              ],
              "query": [],
              "variable": []
            },
            "header": [
              {
                "key": "Content-Type",
                "value": "application/json"
              }
            ],
            "method": "POST",
            "auth": null,
            "body": {
              "mode": "raw",
              "raw": "{\n    \"id\": \"<string>\"\n}"
            }
          },
          "response": [
            {
              "id": "abd6a4a0-fe76-4b34-a2c3-46ca99484566",
              "name": "Success",
              "originalRequest": {
                "url": {
                  "path": [
                    "commands",
                    "DeleteRegistration"
                  ],
                  "host": [
                    "{{baseUrl}}"
                  ],
                  "query": [],
                  "variable": []
                },
                "method": "POST",
                "body": {
                  "mode": "raw",
                  "raw": "{\n    \"id\": \"<string>\"\n}"
                }
              },
              "status": "Accepted",
              "code": 202,
              "header": [
                {
                  "key": "Content-Type",
                  "value": "text/plain"
                }
              ],
              "body": "",
              "cookie": [],
              "_postman_previewlanguage": "text"
            },
            {
              "id": "d233aa57-47d1-466b-b17b-a23d6d30ed06",
              "name": "Unauthorized",
              "originalRequest": {
                "url": {
                  "path": [
                    "commands",
                    "DeleteRegistration"
                  ],
                  "host": [
                    "{{baseUrl}}"
                  ],
                  "query": [],
                  "variable": []
                },
                "method": "POST",
                "body": {
                  "mode": "raw",
                  "raw": "{\n    \"id\": \"<string>\"\n}"
                }
              },
              "status": "Unauthorized",
              "code": 401,
              "header": [
                {
                  "key": "Content-Type",
                  "value": "text/plain"
                }
              ],
              "body": "",
              "cookie": [],
              "_postman_previewlanguage": "text"
            },
            {
              "id": "5b3e39c7-cdb4-464c-9796-ff9b02b206a4",
              "name": "Forbidden",
              "originalRequest": {
                "url": {
                  "path": [
                    "commands",
                    "DeleteRegistration"
                  ],
                  "host": [
                    "{{baseUrl}}"
                  ],
                  "query": [],
                  "variable": []
                },
                "method": "POST",
                "body": {
                  "mode": "raw",
                  "raw": "{\n    \"id\": \"<string>\"\n}"
                }
              },
              "status": "Forbidden",
              "code": 403,
              "header": [
                {
                  "key": "Content-Type",
                  "value": "text/plain"
                }
              ],
              "body": "",
              "cookie": [],
              "_postman_previewlanguage": "text"
            },
            {
              "id": "daaa32cf-fdc0-4bd5-b488-cde6b7c36ea9",
              "name": "Too many requests",
              "originalRequest": {
                "url": {
                  "path": [
                    "commands",
                    "DeleteRegistration"
                  ],
                  "host": [
                    "{{baseUrl}}"
                  ],
                  "query": [],
                  "variable": []
                },
                "method": "POST",
                "body": {
                  "mode": "raw",
                  "raw": "{\n    \"id\": \"<string>\"\n}"
                }
              },
              "status": "Too Many Requests",
              "code": 429,
              "header": [
                {
                  "key": "Content-Type",
                  "value": "text/plain"
                }
              ],
              "body": "",
              "cookie": [],
              "_postman_previewlanguage": "text"
            }
          ],
          "event": []
        },
        {
          "id": "f641f627-4806-4162-95e4-64c1492415c7",
          "name": "/commands/EndRegistration - POST",
          "request": {
            "name": "/commands/EndRegistration - POST",
            "description": {},
            "url": {
              "path": [
                "commands",
                "EndRegistration"
              ],
              "host": [
                "{{baseUrl}}"
              ],
              "query": [],
              "variable": []
            },
            "header": [
              {
                "key": "Content-Type",
                "value": "application/json"
              }
            ],
            "method": "POST",
            "auth": null,
            "body": {
              "mode": "raw",
              "raw": "{\n    \"id\": \"<string>\",\n    \"endUtc\": \"<dateTime>\",\n    \"override\": \"<boolean>\"\n}"
            }
          },
          "response": [
            {
              "id": "602652e4-73e5-4610-b531-102a0b493038",
              "name": "Success",
              "originalRequest": {
                "url": {
                  "path": [
                    "commands",
                    "EndRegistration"
                  ],
                  "host": [
                    "{{baseUrl}}"
                  ],
                  "query": [],
                  "variable": []
                },
                "method": "POST",
                "body": {
                  "mode": "raw",
                  "raw": "{\n    \"id\": \"<string>\",\n    \"endUtc\": \"<dateTime>\",\n    \"override\": \"<boolean>\"\n}"
                }
              },
              "status": "Accepted",
              "code": 202,
              "header": [
                {
                  "key": "Content-Type",
                  "value": "text/plain"
                }
              ],
              "body": "",
              "cookie": [],
              "_postman_previewlanguage": "text"
            },
            {
              "id": "c62dd5ba-c715-4173-988f-fb2ae0cd24b1",
              "name": "Unauthorized",
              "originalRequest": {
                "url": {
                  "path": [
                    "commands",
                    "EndRegistration"
                  ],
                  "host": [
                    "{{baseUrl}}"
                  ],
                  "query": [],
                  "variable": []
                },
                "method": "POST",
                "body": {
                  "mode": "raw",
                  "raw": "{\n    \"id\": \"<string>\",\n    \"endUtc\": \"<dateTime>\",\n    \"override\": \"<boolean>\"\n}"
                }
              },
              "status": "Unauthorized",
              "code": 401,
              "header": [
                {
                  "key": "Content-Type",
                  "value": "text/plain"
                }
              ],
              "body": "",
              "cookie": [],
              "_postman_previewlanguage": "text"
            },
            {
              "id": "aa156952-8d15-4e0c-9432-9fff920703c8",
              "name": "Forbidden",
              "originalRequest": {
                "url": {
                  "path": [
                    "commands",
                    "EndRegistration"
                  ],
                  "host": [
                    "{{baseUrl}}"
                  ],
                  "query": [],
                  "variable": []
                },
                "method": "POST",
                "body": {
                  "mode": "raw",
                  "raw": "{\n    \"id\": \"<string>\",\n    \"endUtc\": \"<dateTime>\",\n    \"override\": \"<boolean>\"\n}"
                }
              },
              "status": "Forbidden",
              "code": 403,
              "header": [
                {
                  "key": "Content-Type",
                  "value": "text/plain"
                }
              ],
              "body": "",
              "cookie": [],
              "_postman_previewlanguage": "text"
            },
            {
              "id": "dcaae6f3-5891-48b0-a10f-83c022977ca5",
              "name": "Too many requests",
              "originalRequest": {
                "url": {
                  "path": [
                    "commands",
                    "EndRegistration"
                  ],
                  "host": [
                    "{{baseUrl}}"
                  ],
                  "query": [],
                  "variable": []
                },
                "method": "POST",
                "body": {
                  "mode": "raw",
                  "raw": "{\n    \"id\": \"<string>\",\n    \"endUtc\": \"<dateTime>\",\n    \"override\": \"<boolean>\"\n}"
                }
              },
              "status": "Too Many Requests",
              "code": 429,
              "header": [
                {
                  "key": "Content-Type",
                  "value": "text/plain"
                }
              ],
              "body": "",
              "cookie": [],
              "_postman_previewlanguage": "text"
            }
          ],
          "event": []
        },
        {
          "id": "bccb6017-faff-434d-b981-448c6840b57b",
          "name": "/commands/RegisterAutomaticOccupancy - POST",
          "request": {
            "name": "/commands/RegisterAutomaticOccupancy - POST",
            "description": {},
            "url": {
              "path": [
                "commands",
                "RegisterAutomaticOccupancy"
              ],
              "host": [
                "{{baseUrl}}"
              ],
              "query": [],
              "variable": []
            },
            "header": [
              {
                "key": "Content-Type",
                "value": "application/json"
              }
            ],
            "method": "POST",
            "auth": null,
            "body": {
              "mode": "raw",
              "raw": "{\n    \"occupancySessionId\": \"<string>\",\n    \"vehicleRegistrationMark\": \"<string>\",\n    \"fullName\": \"<string>\",\n    \"visitedName\": \"<string>\"\n}"
            }
          },
          "response": [
            {
              "id": "8a4aabcb-41b8-4bf2-a395-baad041dc840",
              "name": "Success",
              "originalRequest": {
                "url": {
                  "path": [
                    "commands",
                    "RegisterAutomaticOccupancy"
                  ],
                  "host": [
                    "{{baseUrl}}"
                  ],
                  "query": [],
                  "variable": []
                },
                "method": "POST",
                "body": {
                  "mode": "raw",
                  "raw": "{\n    \"occupancySessionId\": \"<string>\",\n    \"vehicleRegistrationMark\": \"<string>\",\n    \"fullName\": \"<string>\",\n    \"visitedName\": \"<string>\"\n}"
                }
              },
              "status": "Accepted",
              "code": 202,
              "header": [
                {
                  "key": "Content-Type",
                  "value": "text/plain"
                }
              ],
              "body": "",
              "cookie": [],
              "_postman_previewlanguage": "text"
            },
            {
              "id": "37397c19-316d-462a-8885-49d631afb31b",
              "name": "Unauthorized",
              "originalRequest": {
                "url": {
                  "path": [
                    "commands",
                    "RegisterAutomaticOccupancy"
                  ],
                  "host": [
                    "{{baseUrl}}"
                  ],
                  "query": [],
                  "variable": []
                },
                "method": "POST",
                "body": {
                  "mode": "raw",
                  "raw": "{\n    \"occupancySessionId\": \"<string>\",\n    \"vehicleRegistrationMark\": \"<string>\",\n    \"fullName\": \"<string>\",\n    \"visitedName\": \"<string>\"\n}"
                }
              },
              "status": "Unauthorized",
              "code": 401,
              "header": [
                {
                  "key": "Content-Type",
                  "value": "text/plain"
                }
              ],
              "body": "",
              "cookie": [],
              "_postman_previewlanguage": "text"
            },
            {
              "id": "4e1fe8c4-a9be-4fd0-9452-4a630aba4651",
              "name": "Forbidden",
              "originalRequest": {
                "url": {
                  "path": [
                    "commands",
                    "RegisterAutomaticOccupancy"
                  ],
                  "host": [
                    "{{baseUrl}}"
                  ],
                  "query": [],
                  "variable": []
                },
                "method": "POST",
                "body": {
                  "mode": "raw",
                  "raw": "{\n    \"occupancySessionId\": \"<string>\",\n    \"vehicleRegistrationMark\": \"<string>\",\n    \"fullName\": \"<string>\",\n    \"visitedName\": \"<string>\"\n}"
                }
              },
              "status": "Forbidden",
              "code": 403,
              "header": [
                {
                  "key": "Content-Type",
                  "value": "text/plain"
                }
              ],
              "body": "",
              "cookie": [],
              "_postman_previewlanguage": "text"
            },
            {
              "id": "f6860997-68e2-4d43-a233-9eaed768f722",
              "name": "Too many requests",
              "originalRequest": {
                "url": {
                  "path": [
                    "commands",
                    "RegisterAutomaticOccupancy"
                  ],
                  "host": [
                    "{{baseUrl}}"
                  ],
                  "query": [],
                  "variable": []
                },
                "method": "POST",
                "body": {
                  "mode": "raw",
                  "raw": "{\n    \"occupancySessionId\": \"<string>\",\n    \"vehicleRegistrationMark\": \"<string>\",\n    \"fullName\": \"<string>\",\n    \"visitedName\": \"<string>\"\n}"
                }
              },
              "status": "Too Many Requests",
              "code": 429,
              "header": [
                {
                  "key": "Content-Type",
                  "value": "text/plain"
                }
              ],
              "body": "",
              "cookie": [],
              "_postman_previewlanguage": "text"
            }
          ],
          "event": []
        },
        {
          "id": "58d53bc9-3f22-4bd3-87af-80eee0d06a2c",
          "name": "/commands/RegisterManualOccupancy - POST",
          "request": {
            "name": "/commands/RegisterManualOccupancy - POST",
            "description": {},
            "url": {
              "path": [
                "commands",
                "RegisterManualOccupancy"
              ],
              "host": [
                "{{baseUrl}}"
              ],
              "query": [],
              "variable": []
            },
            "header": [
              {
                "key": "Content-Type",
                "value": "application/json"
              }
            ],
            "method": "POST",
            "auth": null,
            "body": {
              "mode": "raw",
              "raw": "{\n    \"parkingAssetId\": \"<string>\",\n    \"bayId\": \"<string>\",\n    \"startUtc\": \"<dateTime>\",\n    \"endUtc\": \"<dateTime>\",\n    \"vehicleRegistrationMark\": \"<string>\",\n    \"fullName\": \"<string>\",\n    \"visitedName\": \"<string>\"\n}"
            }
          },
          "response": [
            {
              "id": "29ad30cc-f7dc-41eb-ab4b-ea90feac2d26",
              "name": "Success",
              "originalRequest": {
                "url": {
                  "path": [
                    "commands",
                    "RegisterManualOccupancy"
                  ],
                  "host": [
                    "{{baseUrl}}"
                  ],
                  "query": [],
                  "variable": []
                },
                "method": "POST",
                "body": {
                  "mode": "raw",
                  "raw": "{\n    \"parkingAssetId\": \"<string>\",\n    \"bayId\": \"<string>\",\n    \"startUtc\": \"<dateTime>\",\n    \"endUtc\": \"<dateTime>\",\n    \"vehicleRegistrationMark\": \"<string>\",\n    \"fullName\": \"<string>\",\n    \"visitedName\": \"<string>\"\n}"
                }
              },
              "status": "Accepted",
              "code": 202,
              "header": [
                {
                  "key": "Content-Type",
                  "value": "text/plain"
                }
              ],
              "body": "",
              "cookie": [],
              "_postman_previewlanguage": "text"
            },
            {
              "id": "3c1fef41-8fb9-449f-8c45-9970848f8ecc",
              "name": "Unauthorized",
              "originalRequest": {
                "url": {
                  "path": [
                    "commands",
                    "RegisterManualOccupancy"
                  ],
                  "host": [
                    "{{baseUrl}}"
                  ],
                  "query": [],
                  "variable": []
                },
                "method": "POST",
                "body": {
                  "mode": "raw",
                  "raw": "{\n    \"parkingAssetId\": \"<string>\",\n    \"bayId\": \"<string>\",\n    \"startUtc\": \"<dateTime>\",\n    \"endUtc\": \"<dateTime>\",\n    \"vehicleRegistrationMark\": \"<string>\",\n    \"fullName\": \"<string>\",\n    \"visitedName\": \"<string>\"\n}"
                }
              },
              "status": "Unauthorized",
              "code": 401,
              "header": [
                {
                  "key": "Content-Type",
                  "value": "text/plain"
                }
              ],
              "body": "",
              "cookie": [],
              "_postman_previewlanguage": "text"
            },
            {
              "id": "45959701-2be0-4553-b978-89ef68fc3334",
              "name": "Forbidden",
              "originalRequest": {
                "url": {
                  "path": [
                    "commands",
                    "RegisterManualOccupancy"
                  ],
                  "host": [
                    "{{baseUrl}}"
                  ],
                  "query": [],
                  "variable": []
                },
                "method": "POST",
                "body": {
                  "mode": "raw",
                  "raw": "{\n    \"parkingAssetId\": \"<string>\",\n    \"bayId\": \"<string>\",\n    \"startUtc\": \"<dateTime>\",\n    \"endUtc\": \"<dateTime>\",\n    \"vehicleRegistrationMark\": \"<string>\",\n    \"fullName\": \"<string>\",\n    \"visitedName\": \"<string>\"\n}"
                }
              },
              "status": "Forbidden",
              "code": 403,
              "header": [
                {
                  "key": "Content-Type",
                  "value": "text/plain"
                }
              ],
              "body": "",
              "cookie": [],
              "_postman_previewlanguage": "text"
            },
            {
              "id": "04067f21-2db8-4b94-ab9a-ca0b1191c4db",
              "name": "Too many requests",
              "originalRequest": {
                "url": {
                  "path": [
                    "commands",
                    "RegisterManualOccupancy"
                  ],
                  "host": [
                    "{{baseUrl}}"
                  ],
                  "query": [],
                  "variable": []
                },
                "method": "POST",
                "body": {
                  "mode": "raw",
                  "raw": "{\n    \"parkingAssetId\": \"<string>\",\n    \"bayId\": \"<string>\",\n    \"startUtc\": \"<dateTime>\",\n    \"endUtc\": \"<dateTime>\",\n    \"vehicleRegistrationMark\": \"<string>\",\n    \"fullName\": \"<string>\",\n    \"visitedName\": \"<string>\"\n}"
                }
              },
              "status": "Too Many Requests",
              "code": 429,
              "header": [
                {
                  "key": "Content-Type",
                  "value": "text/plain"
                }
              ],
              "body": "",
              "cookie": [],
              "_postman_previewlanguage": "text"
            }
          ],
          "event": []
        }
      ],
      "event": []
    },
    {
      "id": "9a9b50b8-89a0-4e3f-8376-a5974128cb21",
      "name": "/monitor - GET",
      "request": {
        "name": "/monitor - GET",
        "description": {},
        "url": {
          "path": [
            "monitor"
          ],
          "host": [
            "{{baseUrl}}"
          ],
          "query": [],
          "variable": []
        },
        "method": "GET",
        "auth": null
      },
      "response": [
        {
          "id": "be0e5cba-02d0-4b07-8c98-dea88bd2718b",
          "name": "Success",
          "originalRequest": {
            "url": {
              "path": [
                "monitor"
              ],
              "host": [
                "{{baseUrl}}"
              ],
              "query": [],
              "variable": []
            },
            "method": "GET",
            "body": {}
          },
          "status": "OK",
          "code": 200,
          "header": [
            {
              "key": "Content-Type",
              "value": "text/plain"
            }
          ],
          "body": "",
          "cookie": [],
          "_postman_previewlanguage": "text"
        },
        {
          "id": "600990e2-0d6e-4bc8-9835-4ce1af681eec",
          "name": "Unauthorized",
          "originalRequest": {
            "url": {
              "path": [
                "monitor"
              ],
              "host": [
                "{{baseUrl}}"
              ],
              "query": [],
              "variable": []
            },
            "method": "GET",
            "body": {}
          },
          "status": "Unauthorized",
          "code": 401,
          "header": [
            {
              "key": "Content-Type",
              "value": "text/plain"
            }
          ],
          "body": "",
          "cookie": [],
          "_postman_previewlanguage": "text"
        },
        {
          "id": "5f116071-4562-4410-a6e8-569400f39b8d",
          "name": "Forbidden",
          "originalRequest": {
            "url": {
              "path": [
                "monitor"
              ],
              "host": [
                "{{baseUrl}}"
              ],
              "query": [],
              "variable": []
            },
            "method": "GET",
            "body": {}
          },
          "status": "Forbidden",
          "code": 403,
          "header": [
            {
              "key": "Content-Type",
              "value": "text/plain"
            }
          ],
          "body": "",
          "cookie": [],
          "_postman_previewlanguage": "text"
        },
        {
          "id": "d7653f1b-47cd-4a9c-8802-bb9f0b96539f",
          "name": "Too many requests",
          "originalRequest": {
            "url": {
              "path": [
                "monitor"
              ],
              "host": [
                "{{baseUrl}}"
              ],
              "query": [],
              "variable": []
            },
            "method": "GET",
            "body": {}
          },
          "status": "Too Many Requests",
          "code": 429,
          "header": [
            {
              "key": "Content-Type",
              "value": "text/plain"
            }
          ],
          "body": "",
          "cookie": [],
          "_postman_previewlanguage": "text"
        }
      ],
      "event": []
    },
    {
      "id": "d60c8c3f-52ad-47d5-9527-981bb0cb937c",
      "name": "queries",
      "item": [
        {
          "id": "1b36105c-c7e8-4f53-8209-2d89e953fee5",
          "name": "/queries/GetActiveRegistrations - GET",
          "request": {
            "name": "/queries/GetActiveRegistrations - GET",
            "description": {},
            "url": {
              "path": [
                "queries",
                "GetActiveRegistrations"
              ],
              "host": [
                "{{baseUrl}}"
              ],
              "query": [
                {
                  "description": "",
                  "key": "ParkingAssetId",
                  "value": "<string>"
                }
              ],
              "variable": []
            },
            "method": "GET",
            "auth": null
          },
          "response": [
            {
              "id": "42adb51e-bc21-4241-8532-0473dbb950cf",
              "name": "Success",
              "originalRequest": {
                "url": {
                  "path": [
                    "queries",
                    "GetActiveRegistrations"
                  ],
                  "host": [
                    "{{baseUrl}}"
                  ],
                  "query": [
                    {
                      "key": "ParkingAssetId",
                      "value": "<string>"
                    }
                  ],
                  "variable": []
                },
                "method": "GET",
                "body": {}
              },
              "status": "OK",
              "code": 200,
              "header": [
                {
                  "key": "Content-Type",
                  "value": "application/json"
                }
              ],
              "body": "[\n {\n  \"id\": \"ut Ut dolore\",\n  \"parkingAssetId\": \"Lorem sunt ea irure\",\n  \"bayId\": \"est\",\n  \"createdOnUtc\": \"incididunt id quis dolor\",\n  \"startUtc\": \"quis elit dolor commodo\",\n  \"endUtc\": \"ad consequat\",\n  \"vehicleRegistrationMark\": \"mollit dolore esse irure officia\",\n  \"fullName\": \"ullamco\",\n  \"visitedName\": \"exercitation cupidatat proident dolore dolor\",\n  \"occupancySessionId\": \"commodo\"\n },\n {\n  \"id\": \"Excepteur qui\",\n  \"parkingAssetId\": \"sed dolore in ex\",\n  \"bayId\": \"tempor Duis\",\n  \"createdOnUtc\": \"reprehenderit amet est in\",\n  \"startUtc\": \"magna in Excepteur officia\",\n  \"endUtc\": \"sunt\",\n  \"vehicleRegistrationMark\": \"in et\",\n  \"fullName\": \"in fugiat ad aliqua magna\",\n  \"visitedName\": \"Excepteur id aute laboris\",\n  \"occupancySessionId\": \"consequat irure Ut ea dolore\"\n }\n]",
              "cookie": [],
              "_postman_previewlanguage": "json"
            },
            {
              "id": "ca06ab4a-5c6e-4c06-9029-73b79c348f63",
              "name": "Unauthorized",
              "originalRequest": {
                "url": {
                  "path": [
                    "queries",
                    "GetActiveRegistrations"
                  ],
                  "host": [
                    "{{baseUrl}}"
                  ],
                  "query": [
                    {
                      "key": "ParkingAssetId",
                      "value": "<string>"
                    }
                  ],
                  "variable": []
                },
                "method": "GET",
                "body": {}
              },
              "status": "Unauthorized",
              "code": 401,
              "header": [
                {
                  "key": "Content-Type",
                  "value": "text/plain"
                }
              ],
              "body": "",
              "cookie": [],
              "_postman_previewlanguage": "text"
            },
            {
              "id": "5decbad7-d7bc-429e-81b2-88be3eb43d32",
              "name": "Forbidden",
              "originalRequest": {
                "url": {
                  "path": [
                    "queries",
                    "GetActiveRegistrations"
                  ],
                  "host": [
                    "{{baseUrl}}"
                  ],
                  "query": [
                    {
                      "key": "ParkingAssetId",
                      "value": "<string>"
                    }
                  ],
                  "variable": []
                },
                "method": "GET",
                "body": {}
              },
              "status": "Forbidden",
              "code": 403,
              "header": [
                {
                  "key": "Content-Type",
                  "value": "text/plain"
                }
              ],
              "body": "",
              "cookie": [],
              "_postman_previewlanguage": "text"
            },
            {
              "id": "256867ef-ba6a-4a12-a3e5-789367e873f3",
              "name": "Too many requests",
              "originalRequest": {
                "url": {
                  "path": [
                    "queries",
                    "GetActiveRegistrations"
                  ],
                  "host": [
                    "{{baseUrl}}"
                  ],
                  "query": [
                    {
                      "key": "ParkingAssetId",
                      "value": "<string>"
                    }
                  ],
                  "variable": []
                },
                "method": "GET",
                "body": {}
              },
              "status": "Too Many Requests",
              "code": 429,
              "header": [
                {
                  "key": "Content-Type",
                  "value": "text/plain"
                }
              ],
              "body": "",
              "cookie": [],
              "_postman_previewlanguage": "text"
            }
          ],
          "event": []
        },
        {
          "id": "057daff3-716b-436e-bca6-797c581257f4",
          "name": "/queries/GetParkingAssetFloors - GET",
          "request": {
            "name": "/queries/GetParkingAssetFloors - GET",
            "description": {},
            "url": {
              "path": [
                "queries",
                "GetParkingAssetFloors"
              ],
              "host": [
                "{{baseUrl}}"
              ],
              "query": [
                {
                  "description": "",
                  "key": "ParkingAssetId",
                  "value": "<string>"
                }
              ],
              "variable": []
            },
            "method": "GET",
            "auth": null
          },
          "response": [
            {
              "id": "8967db26-de3e-45c7-af86-72c3c78d208b",
              "name": "Success",
              "originalRequest": {
                "url": {
                  "path": [
                    "queries",
                    "GetParkingAssetFloors"
                  ],
                  "host": [
                    "{{baseUrl}}"
                  ],
                  "query": [
                    {
                      "key": "ParkingAssetId",
                      "value": "<string>"
                    }
                  ],
                  "variable": []
                },
                "method": "GET",
                "body": {}
              },
              "status": "OK",
              "code": 200,
              "header": [
                {
                  "key": "Content-Type",
                  "value": "application/json"
                }
              ],
              "body": "{\n \"floors\": [\n  {\n   \"id\": \"ut ea sunt commodo\",\n   \"name\": \"reprehenderit est pariatur mollit\",\n   \"ordinal\": 44312609,\n   \"bays\": [\n    {\n     \"id\": \"dolore cupidatat esse\",\n     \"name\": \"exercitation\",\n     \"bayType\": \"do proident\",\n     \"ordinal\": 535919,\n     \"gracePeriod\": -94742503\n    },\n    {\n     \"id\": \"aliqua aute exercitation esse id\",\n     \"name\": \"ad est\",\n     \"bayType\": \"dolore fugiat voluptate\",\n     \"ordinal\": 96623606,\n     \"gracePeriod\": -73428698\n    }\n   ]\n  },\n  {\n   \"id\": \"culpa enim\",\n   \"name\": \"ut e\",\n   \"ordinal\": -99257428,\n   \"bays\": [\n    {\n     \"id\": \"velit magna Duis veniam eiusmod\",\n     \"name\": \"minim adipisicing ut magna\",\n     \"bayType\": \"dolor amet\",\n     \"ordinal\": -88045651,\n     \"gracePeriod\": -43118012\n    },\n    {\n     \"id\": \"sed in ut\",\n     \"name\": \"labore incididunt esse\",\n     \"bayType\": \"sint\",\n     \"ordinal\": 52958690,\n     \"gracePeriod\": -95763537\n    }\n   ]\n  }\n ]\n}",
              "cookie": [],
              "_postman_previewlanguage": "json"
            },
            {
              "id": "49770614-6d91-4b1e-a8f5-1493398ca78d",
              "name": "Unauthorized",
              "originalRequest": {
                "url": {
                  "path": [
                    "queries",
                    "GetParkingAssetFloors"
                  ],
                  "host": [
                    "{{baseUrl}}"
                  ],
                  "query": [
                    {
                      "key": "ParkingAssetId",
                      "value": "<string>"
                    }
                  ],
                  "variable": []
                },
                "method": "GET",
                "body": {}
              },
              "status": "Unauthorized",
              "code": 401,
              "header": [
                {
                  "key": "Content-Type",
                  "value": "text/plain"
                }
              ],
              "body": "",
              "cookie": [],
              "_postman_previewlanguage": "text"
            },
            {
              "id": "3a6a51cd-e94d-4404-94be-51be20592696",
              "name": "Forbidden",
              "originalRequest": {
                "url": {
                  "path": [
                    "queries",
                    "GetParkingAssetFloors"
                  ],
                  "host": [
                    "{{baseUrl}}"
                  ],
                  "query": [
                    {
                      "key": "ParkingAssetId",
                      "value": "<string>"
                    }
                  ],
                  "variable": []
                },
                "method": "GET",
                "body": {}
              },
              "status": "Forbidden",
              "code": 403,
              "header": [
                {
                  "key": "Content-Type",
                  "value": "text/plain"
                }
              ],
              "body": "",
              "cookie": [],
              "_postman_previewlanguage": "text"
            },
            {
              "id": "b5a909dd-d375-4cf0-9513-5e000f1e01ee",
              "name": "Too many requests",
              "originalRequest": {
                "url": {
                  "path": [
                    "queries",
                    "GetParkingAssetFloors"
                  ],
                  "host": [
                    "{{baseUrl}}"
                  ],
                  "query": [
                    {
                      "key": "ParkingAssetId",
                      "value": "<string>"
                    }
                  ],
                  "variable": []
                },
                "method": "GET",
                "body": {}
              },
              "status": "Too Many Requests",
              "code": 429,
              "header": [
                {
                  "key": "Content-Type",
                  "value": "text/plain"
                }
              ],
              "body": "",
              "cookie": [],
              "_postman_previewlanguage": "text"
            }
          ],
          "event": []
        },
        {
          "id": "ea73e968-ac9c-493c-a874-4e1b123ce80d",
          "name": "/queries/GetParkingAssetHeaders - POST",
          "request": {
            "name": "/queries/GetParkingAssetHeaders - POST",
            "description": {},
            "url": {
              "path": [
                "queries",
                "GetParkingAssetHeaders"
              ],
              "host": [
                "{{baseUrl}}"
              ],
              "query": [],
              "variable": []
            },
            "header": [
              {
                "key": "Content-Type",
                "value": "application/json"
              }
            ],
            "method": "POST",
            "auth": null,
            "body": {
              "mode": "raw",
              "raw": "{\n    \"parkingAssetIds\": [\n        \"<string>\",\n        \"<string>\"\n    ]\n}"
            }
          },
          "response": [
            {
              "id": "d1838eb0-5bc1-47d7-88b9-2e9b51d03153",
              "name": "Success",
              "originalRequest": {
                "url": {
                  "path": [
                    "queries",
                    "GetParkingAssetHeaders"
                  ],
                  "host": [
                    "{{baseUrl}}"
                  ],
                  "query": [],
                  "variable": []
                },
                "method": "POST",
                "body": {
                  "mode": "raw",
                  "raw": "{\n    \"parkingAssetIds\": [\n        \"<string>\",\n        \"<string>\"\n    ]\n}"
                }
              },
              "status": "OK",
              "code": 200,
              "header": [
                {
                  "key": "Content-Type",
                  "value": "application/json"
                }
              ],
              "body": "[\n {\n  \"id\": \"est et\",\n  \"name\": \"dol\"\n },\n {\n  \"id\": \"deserunt dolor culpa\",\n  \"name\": \"quis proident nulla\"\n }\n]",
              "cookie": [],
              "_postman_previewlanguage": "json"
            },
            {
              "id": "6fc65453-cf60-41a6-914b-444ca45d059c",
              "name": "Unauthorized",
              "originalRequest": {
                "url": {
                  "path": [
                    "queries",
                    "GetParkingAssetHeaders"
                  ],
                  "host": [
                    "{{baseUrl}}"
                  ],
                  "query": [],
                  "variable": []
                },
                "method": "POST",
                "body": {
                  "mode": "raw",
                  "raw": "{\n    \"parkingAssetIds\": [\n        \"<string>\",\n        \"<string>\"\n    ]\n}"
                }
              },
              "status": "Unauthorized",
              "code": 401,
              "header": [
                {
                  "key": "Content-Type",
                  "value": "text/plain"
                }
              ],
              "body": "",
              "cookie": [],
              "_postman_previewlanguage": "text"
            },
            {
              "id": "78a63795-3f0f-4416-9c53-8589ae63fa9a",
              "name": "Forbidden",
              "originalRequest": {
                "url": {
                  "path": [
                    "queries",
                    "GetParkingAssetHeaders"
                  ],
                  "host": [
                    "{{baseUrl}}"
                  ],
                  "query": [],
                  "variable": []
                },
                "method": "POST",
                "body": {
                  "mode": "raw",
                  "raw": "{\n    \"parkingAssetIds\": [\n        \"<string>\",\n        \"<string>\"\n    ]\n}"
                }
              },
              "status": "Forbidden",
              "code": 403,
              "header": [
                {
                  "key": "Content-Type",
                  "value": "text/plain"
                }
              ],
              "body": "",
              "cookie": [],
              "_postman_previewlanguage": "text"
            },
            {
              "id": "cdeb4a74-c9b5-4a26-8517-2ec32bdeb467",
              "name": "Too many requests",
              "originalRequest": {
                "url": {
                  "path": [
                    "queries",
                    "GetParkingAssetHeaders"
                  ],
                  "host": [
                    "{{baseUrl}}"
                  ],
                  "query": [],
                  "variable": []
                },
                "method": "POST",
                "body": {
                  "mode": "raw",
                  "raw": "{\n    \"parkingAssetIds\": [\n        \"<string>\",\n        \"<string>\"\n    ]\n}"
                }
              },
              "status": "Too Many Requests",
              "code": 429,
              "header": [
                {
                  "key": "Content-Type",
                  "value": "text/plain"
                }
              ],
              "body": "",
              "cookie": [],
              "_postman_previewlanguage": "text"
            }
          ],
          "event": []
        },
        {
          "id": "0c622e95-aefa-40bc-8587-5849925f8451",
          "name": "/queries/GetRecentlyOccupiedBays - GET",
          "request": {
            "name": "/queries/GetRecentlyOccupiedBays - GET",
            "description": {},
            "url": {
              "path": [
                "queries",
                "GetRecentlyOccupiedBays"
              ],
              "host": [
                "{{baseUrl}}"
              ],
              "query": [
                {
                  "description": "",
                  "key": "ParkingAssetId",
                  "value": "<string>"
                }
              ],
              "variable": []
            },
            "method": "GET",
            "auth": null
          },
          "response": [
            {
              "id": "4c5e39cd-fac5-46dc-81d0-0dabad135bc0",
              "name": "Success",
              "originalRequest": {
                "url": {
                  "path": [
                    "queries",
                    "GetRecentlyOccupiedBays"
                  ],
                  "host": [
                    "{{baseUrl}}"
                  ],
                  "query": [
                    {
                      "key": "ParkingAssetId",
                      "value": "<string>"
                    }
                  ],
                  "variable": []
                },
                "method": "GET",
                "body": {}
              },
              "status": "OK",
              "code": 200,
              "header": [
                {
                  "key": "Content-Type",
                  "value": "application/json"
                }
              ],
              "body": "[\n {\n  \"bayId\": \"proident\",\n  \"occupancySessionId\": \"enim reprehenderit est\",\n  \"occupancyStartTimeUtc\": \"incididunt do consequat\"\n },\n {\n  \"bayId\": \"enim fugiat magna\",\n  \"occupancySessionId\": \"in Excepteur eu ipsum\",\n  \"occupancyStartTimeUtc\": \"consecte\"\n }\n]",
              "cookie": [],
              "_postman_previewlanguage": "json"
            },
            {
              "id": "7228d0d3-c33f-4415-9f28-cdb052187439",
              "name": "Unauthorized",
              "originalRequest": {
                "url": {
                  "path": [
                    "queries",
                    "GetRecentlyOccupiedBays"
                  ],
                  "host": [
                    "{{baseUrl}}"
                  ],
                  "query": [
                    {
                      "key": "ParkingAssetId",
                      "value": "<string>"
                    }
                  ],
                  "variable": []
                },
                "method": "GET",
                "body": {}
              },
              "status": "Unauthorized",
              "code": 401,
              "header": [
                {
                  "key": "Content-Type",
                  "value": "text/plain"
                }
              ],
              "body": "",
              "cookie": [],
              "_postman_previewlanguage": "text"
            },
            {
              "id": "68feb9d0-1ca9-42f3-bf27-8c3076741d03",
              "name": "Forbidden",
              "originalRequest": {
                "url": {
                  "path": [
                    "queries",
                    "GetRecentlyOccupiedBays"
                  ],
                  "host": [
                    "{{baseUrl}}"
                  ],
                  "query": [
                    {
                      "key": "ParkingAssetId",
                      "value": "<string>"
                    }
                  ],
                  "variable": []
                },
                "method": "GET",
                "body": {}
              },
              "status": "Forbidden",
              "code": 403,
              "header": [
                {
                  "key": "Content-Type",
                  "value": "text/plain"
                }
              ],
              "body": "",
              "cookie": [],
              "_postman_previewlanguage": "text"
            },
            {
              "id": "3adced44-a18a-474e-9a1f-18771a2bf3f5",
              "name": "Too many requests",
              "originalRequest": {
                "url": {
                  "path": [
                    "queries",
                    "GetRecentlyOccupiedBays"
                  ],
                  "host": [
                    "{{baseUrl}}"
                  ],
                  "query": [
                    {
                      "key": "ParkingAssetId",
                      "value": "<string>"
                    }
                  ],
                  "variable": []
                },
                "method": "GET",
                "body": {}
              },
              "status": "Too Many Requests",
              "code": 429,
              "header": [
                {
                  "key": "Content-Type",
                  "value": "text/plain"
                }
              ],
              "body": "",
              "cookie": [],
              "_postman_previewlanguage": "text"
            }
          ],
          "event": []
        },
        {
          "id": "a055cfcd-e7e7-4310-b5f1-55ac1760fb82",
          "name": "/queries/GetRegistration - GET",
          "request": {
            "name": "/queries/GetRegistration - GET",
            "description": {},
            "url": {
              "path": [
                "queries",
                "GetRegistration"
              ],
              "host": [
                "{{baseUrl}}"
              ],
              "query": [
                {
                  "description": "",
                  "key": "Id",
                  "value": "<string>"
                }
              ],
              "variable": []
            },
            "method": "GET",
            "auth": null
          },
          "response": [
            {
              "id": "d7bcdc97-09e3-4b29-94ea-2a0ee306b427",
              "name": "Success",
              "originalRequest": {
                "url": {
                  "path": [
                    "queries",
                    "GetRegistration"
                  ],
                  "host": [
                    "{{baseUrl}}"
                  ],
                  "query": [
                    {
                      "key": "Id",
                      "value": "<string>"
                    }
                  ],
                  "variable": []
                },
                "method": "GET",
                "body": {}
              },
              "status": "OK",
              "code": 200,
              "header": [
                {
                  "key": "Content-Type",
                  "value": "application/json"
                }
              ],
              "body": "{\n \"id\": \"id\",\n \"parkingAssetId\": \"velit ad sint amet\",\n \"bayId\": \"proident dolor et magna adipisicing\",\n \"createdOnUtc\": \"esse aliqua\",\n \"startUtc\": \"magna proident anim incididunt consequat\",\n \"endUtc\": \"aliqua occaecat\",\n \"vehicleRegistrationMark\": \"Excepteur cupidatat sunt\",\n \"fullName\": \"commodo consectetur velit\",\n \"visitedName\": \"officia ipsum in\",\n \"occupancySessionId\": \"pariatur ea cupid\"\n}",
              "cookie": [],
              "_postman_previewlanguage": "json"
            },
            {
              "id": "dc945286-62a1-47d3-bfa0-8bd81bcbe166",
              "name": "Unauthorized",
              "originalRequest": {
                "url": {
                  "path": [
                    "queries",
                    "GetRegistration"
                  ],
                  "host": [
                    "{{baseUrl}}"
                  ],
                  "query": [
                    {
                      "key": "Id",
                      "value": "<string>"
                    }
                  ],
                  "variable": []
                },
                "method": "GET",
                "body": {}
              },
              "status": "Unauthorized",
              "code": 401,
              "header": [
                {
                  "key": "Content-Type",
                  "value": "text/plain"
                }
              ],
              "body": "",
              "cookie": [],
              "_postman_previewlanguage": "text"
            },
            {
              "id": "95b00d13-53e2-48d6-84c4-97a771bddd21",
              "name": "Forbidden",
              "originalRequest": {
                "url": {
                  "path": [
                    "queries",
                    "GetRegistration"
                  ],
                  "host": [
                    "{{baseUrl}}"
                  ],
                  "query": [
                    {
                      "key": "Id",
                      "value": "<string>"
                    }
                  ],
                  "variable": []
                },
                "method": "GET",
                "body": {}
              },
              "status": "Forbidden",
              "code": 403,
              "header": [
                {
                  "key": "Content-Type",
                  "value": "text/plain"
                }
              ],
              "body": "",
              "cookie": [],
              "_postman_previewlanguage": "text"
            },
            {
              "id": "5220e3bf-b16f-4b9a-b6f6-b1d3d996f92b",
              "name": "Too many requests",
              "originalRequest": {
                "url": {
                  "path": [
                    "queries",
                    "GetRegistration"
                  ],
                  "host": [
                    "{{baseUrl}}"
                  ],
                  "query": [
                    {
                      "key": "Id",
                      "value": "<string>"
                    }
                  ],
                  "variable": []
                },
                "method": "GET",
                "body": {}
              },
              "status": "Too Many Requests",
              "code": 429,
              "header": [
                {
                  "key": "Content-Type",
                  "value": "text/plain"
                }
              ],
              "body": "",
              "cookie": [],
              "_postman_previewlanguage": "text"
            }
          ],
          "event": []
        }
      ],
      "event": []
    }
  ],
  "event": [],
  "variable": [
    {
      "id": "baseUrl",
      "type": "string",
      "value": "https://api.appyway.com/v1/occupancy-authentication"
    }
  ],
  "auth": {
    "type": "apikey",
    "apikey": [
      {
        "key": "value",
        "type": "string",
        "value": "{{API-KEY-LIVE}}"
      },
      {
        "key": "key",
        "type": "string",
        "value": "API-KEY"
      }
    ]
  },
  "info": {
    "_postman_id": "63f091b7-2371-4a0d-a612-1d99215869f9",
    "name": "Occupancy Authentication API (v1.0|LIVE|Public)",
    "schema": "https://schema.getpostman.com/json/collection/v2.1.0/collection.json",
    "description": {
      "content": "",
      "type": "text/plain"
    }
  }
}
