{
  "item": [
    {
      "id": "db003491-0ef5-4c18-a98d-3c4505b0ffff",
      "name": "commands",
      "item": [
        {
          "id": "3849455e-73ad-4705-b001-b691b335efcb",
          "name": "/commands/changeRegistrationDetails - POST",
          "request": {
            "name": "/commands/changeRegistrationDetails - POST",
            "description": {},
            "url": {
              "path": [
                "commands",
                "changeRegistrationDetails"
              ],
              "host": [
                "{{baseUrl}}"
              ],
              "query": [],
              "variable": []
            },
            "header": [
              {
                "key": "Content-Type",
                "value": "application/json"
              }
            ],
            "method": "POST",
            "auth": null,
            "body": {
              "mode": "raw",
              "raw": "{\n    \"id\": \"<string>\",\n    \"startUtc\": \"<dateTime>\",\n    \"endUtc\": \"<dateTime>\",\n    \"vehicleRegistrationMark\": \"<string>\",\n    \"fullName\": \"<string>\",\n    \"visitedName\": \"<string>\"\n}"
            }
          },
          "response": [
            {
              "id": "b235508f-4c13-4a68-a1d3-8adc69bef87e",
              "name": "Success",
              "originalRequest": {
                "url": {
                  "path": [
                    "commands",
                    "changeRegistrationDetails"
                  ],
                  "host": [
                    "{{baseUrl}}"
                  ],
                  "query": [],
                  "variable": []
                },
                "method": "POST",
                "body": {
                  "mode": "raw",
                  "raw": "{\n    \"id\": \"<string>\",\n    \"startUtc\": \"<dateTime>\",\n    \"endUtc\": \"<dateTime>\",\n    \"vehicleRegistrationMark\": \"<string>\",\n    \"fullName\": \"<string>\",\n    \"visitedName\": \"<string>\"\n}"
                }
              },
              "status": "Accepted",
              "code": 202,
              "header": [
                {
                  "key": "Content-Type",
                  "value": "text/plain"
                }
              ],
              "body": "",
              "cookie": [],
              "_postman_previewlanguage": "text"
            },
            {
              "id": "df6eb0bd-dd6f-49b9-aa0b-539d14427f43",
              "name": "Unauthorized",
              "originalRequest": {
                "url": {
                  "path": [
                    "commands",
                    "changeRegistrationDetails"
                  ],
                  "host": [
                    "{{baseUrl}}"
                  ],
                  "query": [],
                  "variable": []
                },
                "method": "POST",
                "body": {
                  "mode": "raw",
                  "raw": "{\n    \"id\": \"<string>\",\n    \"startUtc\": \"<dateTime>\",\n    \"endUtc\": \"<dateTime>\",\n    \"vehicleRegistrationMark\": \"<string>\",\n    \"fullName\": \"<string>\",\n    \"visitedName\": \"<string>\"\n}"
                }
              },
              "status": "Unauthorized",
              "code": 401,
              "header": [
                {
                  "key": "Content-Type",
                  "value": "text/plain"
                }
              ],
              "body": "",
              "cookie": [],
              "_postman_previewlanguage": "text"
            },
            {
              "id": "07b7a1cd-45cc-49e5-98cc-0469040c2a01",
              "name": "Forbidden",
              "originalRequest": {
                "url": {
                  "path": [
                    "commands",
                    "changeRegistrationDetails"
                  ],
                  "host": [
                    "{{baseUrl}}"
                  ],
                  "query": [],
                  "variable": []
                },
                "method": "POST",
                "body": {
                  "mode": "raw",
                  "raw": "{\n    \"id\": \"<string>\",\n    \"startUtc\": \"<dateTime>\",\n    \"endUtc\": \"<dateTime>\",\n    \"vehicleRegistrationMark\": \"<string>\",\n    \"fullName\": \"<string>\",\n    \"visitedName\": \"<string>\"\n}"
                }
              },
              "status": "Forbidden",
              "code": 403,
              "header": [
                {
                  "key": "Content-Type",
                  "value": "text/plain"
                }
              ],
              "body": "",
              "cookie": [],
              "_postman_previewlanguage": "text"
            },
            {
              "id": "c2125c1d-0db8-4629-8d3c-ee10732c8cc1",
              "name": "Too many requests",
              "originalRequest": {
                "url": {
                  "path": [
                    "commands",
                    "changeRegistrationDetails"
                  ],
                  "host": [
                    "{{baseUrl}}"
                  ],
                  "query": [],
                  "variable": []
                },
                "method": "POST",
                "body": {
                  "mode": "raw",
                  "raw": "{\n    \"id\": \"<string>\",\n    \"startUtc\": \"<dateTime>\",\n    \"endUtc\": \"<dateTime>\",\n    \"vehicleRegistrationMark\": \"<string>\",\n    \"fullName\": \"<string>\",\n    \"visitedName\": \"<string>\"\n}"
                }
              },
              "status": "Too Many Requests",
              "code": 429,
              "header": [
                {
                  "key": "Content-Type",
                  "value": "text/plain"
                }
              ],
              "body": "",
              "cookie": [],
              "_postman_previewlanguage": "text"
            }
          ],
          "event": []
        },
        {
          "id": "9fba970c-7d90-40dc-b465-0c5bfa66c285",
          "name": "/commands/deleteRegistration - POST",
          "request": {
            "name": "/commands/deleteRegistration - POST",
            "description": {},
            "url": {
              "path": [
                "commands",
                "deleteRegistration"
              ],
              "host": [
                "{{baseUrl}}"
              ],
              "query": [],
              "variable": []
            },
            "header": [
              {
                "key": "Content-Type",
                "value": "application/json"
              }
            ],
            "method": "POST",
            "auth": null,
            "body": {
              "mode": "raw",
              "raw": "{\n    \"id\": \"<string>\"\n}"
            }
          },
          "response": [
            {
              "id": "479dbc46-be6c-4ea3-a88a-678034d5b810",
              "name": "Success",
              "originalRequest": {
                "url": {
                  "path": [
                    "commands",
                    "deleteRegistration"
                  ],
                  "host": [
                    "{{baseUrl}}"
                  ],
                  "query": [],
                  "variable": []
                },
                "method": "POST",
                "body": {
                  "mode": "raw",
                  "raw": "{\n    \"id\": \"<string>\"\n}"
                }
              },
              "status": "Accepted",
              "code": 202,
              "header": [
                {
                  "key": "Content-Type",
                  "value": "text/plain"
                }
              ],
              "body": "",
              "cookie": [],
              "_postman_previewlanguage": "text"
            },
            {
              "id": "ac565adc-e800-4879-9e05-18961c017653",
              "name": "Unauthorized",
              "originalRequest": {
                "url": {
                  "path": [
                    "commands",
                    "deleteRegistration"
                  ],
                  "host": [
                    "{{baseUrl}}"
                  ],
                  "query": [],
                  "variable": []
                },
                "method": "POST",
                "body": {
                  "mode": "raw",
                  "raw": "{\n    \"id\": \"<string>\"\n}"
                }
              },
              "status": "Unauthorized",
              "code": 401,
              "header": [
                {
                  "key": "Content-Type",
                  "value": "text/plain"
                }
              ],
              "body": "",
              "cookie": [],
              "_postman_previewlanguage": "text"
            },
            {
              "id": "c7592df7-42de-4d20-bcb9-098bbf548d95",
              "name": "Forbidden",
              "originalRequest": {
                "url": {
                  "path": [
                    "commands",
                    "deleteRegistration"
                  ],
                  "host": [
                    "{{baseUrl}}"
                  ],
                  "query": [],
                  "variable": []
                },
                "method": "POST",
                "body": {
                  "mode": "raw",
                  "raw": "{\n    \"id\": \"<string>\"\n}"
                }
              },
              "status": "Forbidden",
              "code": 403,
              "header": [
                {
                  "key": "Content-Type",
                  "value": "text/plain"
                }
              ],
              "body": "",
              "cookie": [],
              "_postman_previewlanguage": "text"
            },
            {
              "id": "e63159b1-7d45-4a93-8c54-d8d7da3227f1",
              "name": "Too many requests",
              "originalRequest": {
                "url": {
                  "path": [
                    "commands",
                    "deleteRegistration"
                  ],
                  "host": [
                    "{{baseUrl}}"
                  ],
                  "query": [],
                  "variable": []
                },
                "method": "POST",
                "body": {
                  "mode": "raw",
                  "raw": "{\n    \"id\": \"<string>\"\n}"
                }
              },
              "status": "Too Many Requests",
              "code": 429,
              "header": [
                {
                  "key": "Content-Type",
                  "value": "text/plain"
                }
              ],
              "body": "",
              "cookie": [],
              "_postman_previewlanguage": "text"
            }
          ],
          "event": []
        },
        {
          "id": "1e193953-c7a1-497a-84a7-002f5a75af1d",
          "name": "/commands/endRegistration - POST",
          "request": {
            "name": "/commands/endRegistration - POST",
            "description": {},
            "url": {
              "path": [
                "commands",
                "endRegistration"
              ],
              "host": [
                "{{baseUrl}}"
              ],
              "query": [],
              "variable": []
            },
            "header": [
              {
                "key": "Content-Type",
                "value": "application/json"
              }
            ],
            "method": "POST",
            "auth": null,
            "body": {
              "mode": "raw",
              "raw": "{\n    \"id\": \"<string>\",\n    \"endUtc\": \"<dateTime>\",\n    \"override\": \"<boolean>\"\n}"
            }
          },
          "response": [
            {
              "id": "41541102-cad4-4f8e-a484-261a8a576f63",
              "name": "Success",
              "originalRequest": {
                "url": {
                  "path": [
                    "commands",
                    "endRegistration"
                  ],
                  "host": [
                    "{{baseUrl}}"
                  ],
                  "query": [],
                  "variable": []
                },
                "method": "POST",
                "body": {
                  "mode": "raw",
                  "raw": "{\n    \"id\": \"<string>\",\n    \"endUtc\": \"<dateTime>\",\n    \"override\": \"<boolean>\"\n}"
                }
              },
              "status": "Accepted",
              "code": 202,
              "header": [
                {
                  "key": "Content-Type",
                  "value": "text/plain"
                }
              ],
              "body": "",
              "cookie": [],
              "_postman_previewlanguage": "text"
            },
            {
              "id": "d5f26504-6563-4ec9-afdf-fd5b386e62e8",
              "name": "Unauthorized",
              "originalRequest": {
                "url": {
                  "path": [
                    "commands",
                    "endRegistration"
                  ],
                  "host": [
                    "{{baseUrl}}"
                  ],
                  "query": [],
                  "variable": []
                },
                "method": "POST",
                "body": {
                  "mode": "raw",
                  "raw": "{\n    \"id\": \"<string>\",\n    \"endUtc\": \"<dateTime>\",\n    \"override\": \"<boolean>\"\n}"
                }
              },
              "status": "Unauthorized",
              "code": 401,
              "header": [
                {
                  "key": "Content-Type",
                  "value": "text/plain"
                }
              ],
              "body": "",
              "cookie": [],
              "_postman_previewlanguage": "text"
            },
            {
              "id": "1d7978fd-b9f0-48c3-b93d-386d6c3e887b",
              "name": "Forbidden",
              "originalRequest": {
                "url": {
                  "path": [
                    "commands",
                    "endRegistration"
                  ],
                  "host": [
                    "{{baseUrl}}"
                  ],
                  "query": [],
                  "variable": []
                },
                "method": "POST",
                "body": {
                  "mode": "raw",
                  "raw": "{\n    \"id\": \"<string>\",\n    \"endUtc\": \"<dateTime>\",\n    \"override\": \"<boolean>\"\n}"
                }
              },
              "status": "Forbidden",
              "code": 403,
              "header": [
                {
                  "key": "Content-Type",
                  "value": "text/plain"
                }
              ],
              "body": "",
              "cookie": [],
              "_postman_previewlanguage": "text"
            },
            {
              "id": "5e99ef49-d0ef-4cea-8567-e84a1321e2f5",
              "name": "Too many requests",
              "originalRequest": {
                "url": {
                  "path": [
                    "commands",
                    "endRegistration"
                  ],
                  "host": [
                    "{{baseUrl}}"
                  ],
                  "query": [],
                  "variable": []
                },
                "method": "POST",
                "body": {
                  "mode": "raw",
                  "raw": "{\n    \"id\": \"<string>\",\n    \"endUtc\": \"<dateTime>\",\n    \"override\": \"<boolean>\"\n}"
                }
              },
              "status": "Too Many Requests",
              "code": 429,
              "header": [
                {
                  "key": "Content-Type",
                  "value": "text/plain"
                }
              ],
              "body": "",
              "cookie": [],
              "_postman_previewlanguage": "text"
            }
          ],
          "event": []
        },
        {
          "id": "cb9424b5-233e-4f3c-a0f4-6188efb8af37",
          "name": "/commands/registerAutomaticOccupancy - POST",
          "request": {
            "name": "/commands/registerAutomaticOccupancy - POST",
            "description": {},
            "url": {
              "path": [
                "commands",
                "registerAutomaticOccupancy"
              ],
              "host": [
                "{{baseUrl}}"
              ],
              "query": [],
              "variable": []
            },
            "header": [
              {
                "key": "Content-Type",
                "value": "application/json"
              }
            ],
            "method": "POST",
            "auth": null,
            "body": {
              "mode": "raw",
              "raw": "{\n    \"occupancySessionId\": \"<string>\",\n    \"vehicleRegistrationMark\": \"<string>\",\n    \"fullName\": \"<string>\",\n    \"visitedName\": \"<string>\"\n}"
            }
          },
          "response": [
            {
              "id": "75944561-1892-4ba1-af7d-ca93b21b74e4",
              "name": "Success",
              "originalRequest": {
                "url": {
                  "path": [
                    "commands",
                    "registerAutomaticOccupancy"
                  ],
                  "host": [
                    "{{baseUrl}}"
                  ],
                  "query": [],
                  "variable": []
                },
                "method": "POST",
                "body": {
                  "mode": "raw",
                  "raw": "{\n    \"occupancySessionId\": \"<string>\",\n    \"vehicleRegistrationMark\": \"<string>\",\n    \"fullName\": \"<string>\",\n    \"visitedName\": \"<string>\"\n}"
                }
              },
              "status": "Accepted",
              "code": 202,
              "header": [
                {
                  "key": "Content-Type",
                  "value": "text/plain"
                }
              ],
              "body": "",
              "cookie": [],
              "_postman_previewlanguage": "text"
            },
            {
              "id": "148f12b6-8e75-4217-843f-1c5d091518e6",
              "name": "Unauthorized",
              "originalRequest": {
                "url": {
                  "path": [
                    "commands",
                    "registerAutomaticOccupancy"
                  ],
                  "host": [
                    "{{baseUrl}}"
                  ],
                  "query": [],
                  "variable": []
                },
                "method": "POST",
                "body": {
                  "mode": "raw",
                  "raw": "{\n    \"occupancySessionId\": \"<string>\",\n    \"vehicleRegistrationMark\": \"<string>\",\n    \"fullName\": \"<string>\",\n    \"visitedName\": \"<string>\"\n}"
                }
              },
              "status": "Unauthorized",
              "code": 401,
              "header": [
                {
                  "key": "Content-Type",
                  "value": "text/plain"
                }
              ],
              "body": "",
              "cookie": [],
              "_postman_previewlanguage": "text"
            },
            {
              "id": "242ef8be-e618-4c5c-bb3d-58a910f77464",
              "name": "Forbidden",
              "originalRequest": {
                "url": {
                  "path": [
                    "commands",
                    "registerAutomaticOccupancy"
                  ],
                  "host": [
                    "{{baseUrl}}"
                  ],
                  "query": [],
                  "variable": []
                },
                "method": "POST",
                "body": {
                  "mode": "raw",
                  "raw": "{\n    \"occupancySessionId\": \"<string>\",\n    \"vehicleRegistrationMark\": \"<string>\",\n    \"fullName\": \"<string>\",\n    \"visitedName\": \"<string>\"\n}"
                }
              },
              "status": "Forbidden",
              "code": 403,
              "header": [
                {
                  "key": "Content-Type",
                  "value": "text/plain"
                }
              ],
              "body": "",
              "cookie": [],
              "_postman_previewlanguage": "text"
            },
            {
              "id": "5d9559f5-42e5-4a45-b86b-87dcefa0dd88",
              "name": "Too many requests",
              "originalRequest": {
                "url": {
                  "path": [
                    "commands",
                    "registerAutomaticOccupancy"
                  ],
                  "host": [
                    "{{baseUrl}}"
                  ],
                  "query": [],
                  "variable": []
                },
                "method": "POST",
                "body": {
                  "mode": "raw",
                  "raw": "{\n    \"occupancySessionId\": \"<string>\",\n    \"vehicleRegistrationMark\": \"<string>\",\n    \"fullName\": \"<string>\",\n    \"visitedName\": \"<string>\"\n}"
                }
              },
              "status": "Too Many Requests",
              "code": 429,
              "header": [
                {
                  "key": "Content-Type",
                  "value": "text/plain"
                }
              ],
              "body": "",
              "cookie": [],
              "_postman_previewlanguage": "text"
            }
          ],
          "event": []
        },
        {
          "id": "553287f9-8b9c-4bd6-a2ff-c3c4f84b3086",
          "name": "/commands/registerManualOccupancy - POST",
          "request": {
            "name": "/commands/registerManualOccupancy - POST",
            "description": {},
            "url": {
              "path": [
                "commands",
                "registerManualOccupancy"
              ],
              "host": [
                "{{baseUrl}}"
              ],
              "query": [],
              "variable": []
            },
            "header": [
              {
                "key": "Content-Type",
                "value": "application/json"
              }
            ],
            "method": "POST",
            "auth": null,
            "body": {
              "mode": "raw",
              "raw": "{\n    \"parkingAssetId\": \"<string>\",\n    \"bayId\": \"<string>\",\n    \"startUtc\": \"<dateTime>\",\n    \"endUtc\": \"<dateTime>\",\n    \"vehicleRegistrationMark\": \"<string>\",\n    \"fullName\": \"<string>\",\n    \"visitedName\": \"<string>\"\n}"
            }
          },
          "response": [
            {
              "id": "8ad321cd-fab2-4945-a28d-a40918b2bbbf",
              "name": "Success",
              "originalRequest": {
                "url": {
                  "path": [
                    "commands",
                    "registerManualOccupancy"
                  ],
                  "host": [
                    "{{baseUrl}}"
                  ],
                  "query": [],
                  "variable": []
                },
                "method": "POST",
                "body": {
                  "mode": "raw",
                  "raw": "{\n    \"parkingAssetId\": \"<string>\",\n    \"bayId\": \"<string>\",\n    \"startUtc\": \"<dateTime>\",\n    \"endUtc\": \"<dateTime>\",\n    \"vehicleRegistrationMark\": \"<string>\",\n    \"fullName\": \"<string>\",\n    \"visitedName\": \"<string>\"\n}"
                }
              },
              "status": "Accepted",
              "code": 202,
              "header": [
                {
                  "key": "Content-Type",
                  "value": "text/plain"
                }
              ],
              "body": "",
              "cookie": [],
              "_postman_previewlanguage": "text"
            },
            {
              "id": "d7cdb463-6bf6-42f2-944f-b24dee370148",
              "name": "Unauthorized",
              "originalRequest": {
                "url": {
                  "path": [
                    "commands",
                    "registerManualOccupancy"
                  ],
                  "host": [
                    "{{baseUrl}}"
                  ],
                  "query": [],
                  "variable": []
                },
                "method": "POST",
                "body": {
                  "mode": "raw",
                  "raw": "{\n    \"parkingAssetId\": \"<string>\",\n    \"bayId\": \"<string>\",\n    \"startUtc\": \"<dateTime>\",\n    \"endUtc\": \"<dateTime>\",\n    \"vehicleRegistrationMark\": \"<string>\",\n    \"fullName\": \"<string>\",\n    \"visitedName\": \"<string>\"\n}"
                }
              },
              "status": "Unauthorized",
              "code": 401,
              "header": [
                {
                  "key": "Content-Type",
                  "value": "text/plain"
                }
              ],
              "body": "",
              "cookie": [],
              "_postman_previewlanguage": "text"
            },
            {
              "id": "15c8000e-5c7b-4de5-ab1b-39be5d0a9651",
              "name": "Forbidden",
              "originalRequest": {
                "url": {
                  "path": [
                    "commands",
                    "registerManualOccupancy"
                  ],
                  "host": [
                    "{{baseUrl}}"
                  ],
                  "query": [],
                  "variable": []
                },
                "method": "POST",
                "body": {
                  "mode": "raw",
                  "raw": "{\n    \"parkingAssetId\": \"<string>\",\n    \"bayId\": \"<string>\",\n    \"startUtc\": \"<dateTime>\",\n    \"endUtc\": \"<dateTime>\",\n    \"vehicleRegistrationMark\": \"<string>\",\n    \"fullName\": \"<string>\",\n    \"visitedName\": \"<string>\"\n}"
                }
              },
              "status": "Forbidden",
              "code": 403,
              "header": [
                {
                  "key": "Content-Type",
                  "value": "text/plain"
                }
              ],
              "body": "",
              "cookie": [],
              "_postman_previewlanguage": "text"
            },
            {
              "id": "905ccca3-3bf5-4b1e-99ef-990fc6bc85dc",
              "name": "Too many requests",
              "originalRequest": {
                "url": {
                  "path": [
                    "commands",
                    "registerManualOccupancy"
                  ],
                  "host": [
                    "{{baseUrl}}"
                  ],
                  "query": [],
                  "variable": []
                },
                "method": "POST",
                "body": {
                  "mode": "raw",
                  "raw": "{\n    \"parkingAssetId\": \"<string>\",\n    \"bayId\": \"<string>\",\n    \"startUtc\": \"<dateTime>\",\n    \"endUtc\": \"<dateTime>\",\n    \"vehicleRegistrationMark\": \"<string>\",\n    \"fullName\": \"<string>\",\n    \"visitedName\": \"<string>\"\n}"
                }
              },
              "status": "Too Many Requests",
              "code": 429,
              "header": [
                {
                  "key": "Content-Type",
                  "value": "text/plain"
                }
              ],
              "body": "",
              "cookie": [],
              "_postman_previewlanguage": "text"
            }
          ],
          "event": []
        }
      ],
      "event": []
    },
    {
      "id": "8ddb0464-ef72-4b93-9d47-ba3ac4c21301",
      "name": "Monitor",
      "request": {
        "name": "Monitor",
        "description": {
          "content": "Returns information on the health of the OccupancyAuthentication API service",
          "type": "text/plain"
        },
        "url": {
          "path": [
            "monitor"
          ],
          "host": [
            "{{baseUrl}}"
          ],
          "query": [],
          "variable": []
        },
        "method": "GET",
        "auth": null
      },
      "response": [
        {
          "id": "0f231ccb-78c1-4582-8333-bce17bc79d0f",
          "name": "Success",
          "originalRequest": {
            "url": {
              "path": [
                "monitor"
              ],
              "host": [
                "{{baseUrl}}"
              ],
              "query": [],
              "variable": []
            },
            "method": "GET",
            "body": {}
          },
          "status": "OK",
          "code": 200,
          "header": [
            {
              "key": "Content-Type",
              "value": "text/plain"
            }
          ],
          "body": "",
          "cookie": [],
          "_postman_previewlanguage": "text"
        },
        {
          "id": "2024e022-7890-4605-9312-636cf06e1ae9",
          "name": "Unauthorized",
          "originalRequest": {
            "url": {
              "path": [
                "monitor"
              ],
              "host": [
                "{{baseUrl}}"
              ],
              "query": [],
              "variable": []
            },
            "method": "GET",
            "body": {}
          },
          "status": "Unauthorized",
          "code": 401,
          "header": [
            {
              "key": "Content-Type",
              "value": "text/plain"
            }
          ],
          "body": "",
          "cookie": [],
          "_postman_previewlanguage": "text"
        },
        {
          "id": "c1e6a4f9-06b9-44be-a395-49ce190a7c63",
          "name": "Forbidden",
          "originalRequest": {
            "url": {
              "path": [
                "monitor"
              ],
              "host": [
                "{{baseUrl}}"
              ],
              "query": [],
              "variable": []
            },
            "method": "GET",
            "body": {}
          },
          "status": "Forbidden",
          "code": 403,
          "header": [
            {
              "key": "Content-Type",
              "value": "text/plain"
            }
          ],
          "body": "",
          "cookie": [],
          "_postman_previewlanguage": "text"
        },
        {
          "id": "89a0ecf3-ee9b-43ef-bcc5-f9ccee325781",
          "name": "Too many requests",
          "originalRequest": {
            "url": {
              "path": [
                "monitor"
              ],
              "host": [
                "{{baseUrl}}"
              ],
              "query": [],
              "variable": []
            },
            "method": "GET",
            "body": {}
          },
          "status": "Too Many Requests",
          "code": 429,
          "header": [
            {
              "key": "Content-Type",
              "value": "text/plain"
            }
          ],
          "body": "",
          "cookie": [],
          "_postman_previewlanguage": "text"
        }
      ],
      "event": []
    },
    {
      "id": "46463859-70cf-4ea8-a446-07177daaecd7",
      "name": "queries",
      "item": [
        {
          "id": "a399fe64-3fcd-4fbe-8d6d-828d89c76dc6",
          "name": "/queries/getActiveRegistrations - POST",
          "request": {
            "name": "/queries/getActiveRegistrations - POST",
            "description": {},
            "url": {
              "path": [
                "queries",
                "getActiveRegistrations"
              ],
              "host": [
                "{{baseUrl}}"
              ],
              "query": [],
              "variable": []
            },
            "header": [
              {
                "key": "Content-Type",
                "value": "application/json"
              }
            ],
            "method": "POST",
            "auth": null,
            "body": {
              "mode": "raw",
              "raw": "{\n    \"parkingAssetId\": \"<string>\"\n}"
            }
          },
          "response": [
            {
              "id": "42dbd9b3-ca93-4f5e-9c83-b3fcbfdc47f7",
              "name": "Success",
              "originalRequest": {
                "url": {
                  "path": [
                    "queries",
                    "getActiveRegistrations"
                  ],
                  "host": [
                    "{{baseUrl}}"
                  ],
                  "query": [],
                  "variable": []
                },
                "method": "POST",
                "body": {
                  "mode": "raw",
                  "raw": "{\n    \"parkingAssetId\": \"<string>\"\n}"
                }
              },
              "status": "OK",
              "code": 200,
              "header": [
                {
                  "key": "Content-Type",
                  "value": "application/json"
                }
              ],
              "body": "{\n \"success\": true,\n \"result\": [\n  {\n   \"id\": \"proident occaecat ad dolor ut\",\n   \"parkingAssetId\": \"laborum sint irur\",\n   \"bayId\": \"Ut sit am\",\n   \"createdOnUtc\": \"ut aliqua occaecat sunt\",\n   \"startUtc\": \"ex\",\n   \"endUtc\": \"ex reprehenderit aliqua elit\",\n   \"vehicleRegistrationMark\": \"amet non ex nulla\",\n   \"fullName\": \"mollit aliqua ex\",\n   \"visitedName\": \"in veniam\",\n   \"occupancySessionId\": \"et\"\n  },\n  {\n   \"id\": \"cillum esse adipisicing officia\",\n   \"parkingAssetId\": \"laboris Ut elit id\",\n   \"bayId\": \"ad occaecat dolore\",\n   \"createdOnUtc\": \"tempor dolor occaecat \",\n   \"startUtc\": \"elit nostrud quis\",\n   \"endUtc\": \"dolor culpa\",\n   \"vehicleRegistrationMark\": \"id incididunt officia velit\",\n   \"fullName\": \"in enim do consectetur\",\n   \"visitedName\": \"elit\",\n   \"occupancySessionId\": \"mollit est Ut veniam qui\"\n  }\n ]\n}",
              "cookie": [],
              "_postman_previewlanguage": "json"
            },
            {
              "id": "1b39f95e-fd9c-4ce9-bf9d-0f8e60c8aca9",
              "name": "Bad Request",
              "originalRequest": {
                "url": {
                  "path": [
                    "queries",
                    "getActiveRegistrations"
                  ],
                  "host": [
                    "{{baseUrl}}"
                  ],
                  "query": [],
                  "variable": []
                },
                "method": "POST",
                "body": {
                  "mode": "raw",
                  "raw": "{\n    \"parkingAssetId\": \"<string>\"\n}"
                }
              },
              "status": "Bad Request",
              "code": 400,
              "header": [
                {
                  "key": "Content-Type",
                  "value": "application/json"
                }
              ],
              "body": "{\n \"success\": false,\n \"message\": \"occaecat \",\n \"errors\": [\n  {\n   \"property\": \"ut laboris nisi dolor\",\n   \"code\": \"sint\",\n   \"message\": \"commodo dolor mollit et\"\n  },\n  {\n   \"property\": \"non\",\n   \"code\": \"enim aliquip ex nostrud\",\n   \"message\": \"ut in dolore\"\n  }\n ]\n}",
              "cookie": [],
              "_postman_previewlanguage": "json"
            },
            {
              "id": "9ba81786-45a6-4c6c-89e5-0da8298668a2",
              "name": "Unauthorized",
              "originalRequest": {
                "url": {
                  "path": [
                    "queries",
                    "getActiveRegistrations"
                  ],
                  "host": [
                    "{{baseUrl}}"
                  ],
                  "query": [],
                  "variable": []
                },
                "method": "POST",
                "body": {
                  "mode": "raw",
                  "raw": "{\n    \"parkingAssetId\": \"<string>\"\n}"
                }
              },
              "status": "Unauthorized",
              "code": 401,
              "header": [
                {
                  "key": "Content-Type",
                  "value": "text/plain"
                }
              ],
              "body": "",
              "cookie": [],
              "_postman_previewlanguage": "text"
            },
            {
              "id": "08c19567-43f6-463a-b122-1e181b1ca4d5",
              "name": "Forbidden",
              "originalRequest": {
                "url": {
                  "path": [
                    "queries",
                    "getActiveRegistrations"
                  ],
                  "host": [
                    "{{baseUrl}}"
                  ],
                  "query": [],
                  "variable": []
                },
                "method": "POST",
                "body": {
                  "mode": "raw",
                  "raw": "{\n    \"parkingAssetId\": \"<string>\"\n}"
                }
              },
              "status": "Forbidden",
              "code": 403,
              "header": [
                {
                  "key": "Content-Type",
                  "value": "text/plain"
                }
              ],
              "body": "",
              "cookie": [],
              "_postman_previewlanguage": "text"
            },
            {
              "id": "9cdfeb17-4353-4d07-9cd3-cddc4307e344",
              "name": "Too many requests",
              "originalRequest": {
                "url": {
                  "path": [
                    "queries",
                    "getActiveRegistrations"
                  ],
                  "host": [
                    "{{baseUrl}}"
                  ],
                  "query": [],
                  "variable": []
                },
                "method": "POST",
                "body": {
                  "mode": "raw",
                  "raw": "{\n    \"parkingAssetId\": \"<string>\"\n}"
                }
              },
              "status": "Too Many Requests",
              "code": 429,
              "header": [
                {
                  "key": "Content-Type",
                  "value": "text/plain"
                }
              ],
              "body": "",
              "cookie": [],
              "_postman_previewlanguage": "text"
            }
          ],
          "event": []
        },
        {
          "id": "3af0ac65-1de7-4a81-9060-cd10036b06c0",
          "name": "/queries/getParkingAssetFloors - POST",
          "request": {
            "name": "/queries/getParkingAssetFloors - POST",
            "description": {},
            "url": {
              "path": [
                "queries",
                "getParkingAssetFloors"
              ],
              "host": [
                "{{baseUrl}}"
              ],
              "query": [],
              "variable": []
            },
            "header": [
              {
                "key": "Content-Type",
                "value": "application/json"
              }
            ],
            "method": "POST",
            "auth": null,
            "body": {
              "mode": "raw",
              "raw": "{\n    \"parkingAssetId\": \"<string>\"\n}"
            }
          },
          "response": [
            {
              "id": "411c8bca-b29c-460b-938e-e3013bdf0cfd",
              "name": "Success",
              "originalRequest": {
                "url": {
                  "path": [
                    "queries",
                    "getParkingAssetFloors"
                  ],
                  "host": [
                    "{{baseUrl}}"
                  ],
                  "query": [],
                  "variable": []
                },
                "method": "POST",
                "body": {
                  "mode": "raw",
                  "raw": "{\n    \"parkingAssetId\": \"<string>\"\n}"
                }
              },
              "status": "OK",
              "code": 200,
              "header": [
                {
                  "key": "Content-Type",
                  "value": "application/json"
                }
              ],
              "body": "{\n \"success\": true,\n \"result\": {\n  \"floors\": [\n   {\n    \"id\": \"anim irure\",\n    \"name\": \"in qui ipsum\",\n    \"ordinal\": 93885050,\n    \"bays\": [\n     {\n      \"id\": \"cillum incididunt dolor\",\n      \"name\": \"consectetur dolor\",\n      \"bayType\": \"proident non enim\",\n      \"ordinal\": -59334664,\n      \"gracePeriod\": 31311253\n     },\n     {\n      \"id\": \"cupidatat culpa\",\n      \"name\": \"commodo e\",\n      \"bayType\": \"ad commodo aliquip mollit in\",\n      \"ordinal\": 47876203,\n      \"gracePeriod\": 40336288\n     }\n    ]\n   },\n   {\n    \"id\": \"et irure proident amet\",\n    \"name\": \"dolor magna commodo\",\n    \"ordinal\": 58218505,\n    \"bays\": [\n     {\n      \"id\": \"qui si\",\n      \"name\": \"ut qui in sint sit\",\n      \"bayType\": \"nulla officia\",\n      \"ordinal\": 77214816,\n      \"gracePeriod\": 29151233\n     },\n     {\n      \"id\": \"ut\",\n      \"name\": \"reprehenderit Ut in\",\n      \"bayType\": \"incididunt nostrud a\",\n      \"ordinal\": -6323073,\n      \"gracePeriod\": -99382233\n     }\n    ]\n   }\n  ]\n }\n}",
              "cookie": [],
              "_postman_previewlanguage": "json"
            },
            {
              "id": "3f3b6a31-cd80-4c29-af54-8bf5e7683113",
              "name": "Bad Request",
              "originalRequest": {
                "url": {
                  "path": [
                    "queries",
                    "getParkingAssetFloors"
                  ],
                  "host": [
                    "{{baseUrl}}"
                  ],
                  "query": [],
                  "variable": []
                },
                "method": "POST",
                "body": {
                  "mode": "raw",
                  "raw": "{\n    \"parkingAssetId\": \"<string>\"\n}"
                }
              },
              "status": "Bad Request",
              "code": 400,
              "header": [
                {
                  "key": "Content-Type",
                  "value": "application/json"
                }
              ],
              "body": "{\n \"success\": false,\n \"message\": \"et non ut elit\",\n \"errors\": [\n  {\n   \"property\": \"Lorem eiusmod\",\n   \"code\": \"enim non\",\n   \"message\": \"ad in\"\n  },\n  {\n   \"property\": \"sit ullamco nulla\",\n   \"code\": \"esse proident cupidatat Lorem nulla\",\n   \"message\": \"velit et nisi sint\"\n  }\n ]\n}",
              "cookie": [],
              "_postman_previewlanguage": "json"
            },
            {
              "id": "8fd1c5ca-6c61-432b-8f78-6cb65a9957bf",
              "name": "Unauthorized",
              "originalRequest": {
                "url": {
                  "path": [
                    "queries",
                    "getParkingAssetFloors"
                  ],
                  "host": [
                    "{{baseUrl}}"
                  ],
                  "query": [],
                  "variable": []
                },
                "method": "POST",
                "body": {
                  "mode": "raw",
                  "raw": "{\n    \"parkingAssetId\": \"<string>\"\n}"
                }
              },
              "status": "Unauthorized",
              "code": 401,
              "header": [
                {
                  "key": "Content-Type",
                  "value": "text/plain"
                }
              ],
              "body": "",
              "cookie": [],
              "_postman_previewlanguage": "text"
            },
            {
              "id": "25ce00a4-afb8-41d8-b5ef-bc70f52a674a",
              "name": "Forbidden",
              "originalRequest": {
                "url": {
                  "path": [
                    "queries",
                    "getParkingAssetFloors"
                  ],
                  "host": [
                    "{{baseUrl}}"
                  ],
                  "query": [],
                  "variable": []
                },
                "method": "POST",
                "body": {
                  "mode": "raw",
                  "raw": "{\n    \"parkingAssetId\": \"<string>\"\n}"
                }
              },
              "status": "Forbidden",
              "code": 403,
              "header": [
                {
                  "key": "Content-Type",
                  "value": "text/plain"
                }
              ],
              "body": "",
              "cookie": [],
              "_postman_previewlanguage": "text"
            },
            {
              "id": "91b24b09-32de-47a3-acfe-7efee9df97d8",
              "name": "Too many requests",
              "originalRequest": {
                "url": {
                  "path": [
                    "queries",
                    "getParkingAssetFloors"
                  ],
                  "host": [
                    "{{baseUrl}}"
                  ],
                  "query": [],
                  "variable": []
                },
                "method": "POST",
                "body": {
                  "mode": "raw",
                  "raw": "{\n    \"parkingAssetId\": \"<string>\"\n}"
                }
              },
              "status": "Too Many Requests",
              "code": 429,
              "header": [
                {
                  "key": "Content-Type",
                  "value": "text/plain"
                }
              ],
              "body": "",
              "cookie": [],
              "_postman_previewlanguage": "text"
            }
          ],
          "event": []
        },
        {
          "id": "d5de3d4c-1e70-4f0e-a38f-3edb483e3084",
          "name": "/queries/getParkingAssetHeaders - POST",
          "request": {
            "name": "/queries/getParkingAssetHeaders - POST",
            "description": {},
            "url": {
              "path": [
                "queries",
                "getParkingAssetHeaders"
              ],
              "host": [
                "{{baseUrl}}"
              ],
              "query": [],
              "variable": []
            },
            "header": [
              {
                "key": "Content-Type",
                "value": "application/json"
              }
            ],
            "method": "POST",
            "auth": null,
            "body": {
              "mode": "raw",
              "raw": "{\n    \"parkingAssetIds\": [\n        \"<string>\",\n        \"<string>\"\n    ]\n}"
            }
          },
          "response": [
            {
              "id": "ae8db2fb-46e5-4839-9009-14f2f9d1532b",
              "name": "Success",
              "originalRequest": {
                "url": {
                  "path": [
                    "queries",
                    "getParkingAssetHeaders"
                  ],
                  "host": [
                    "{{baseUrl}}"
                  ],
                  "query": [],
                  "variable": []
                },
                "method": "POST",
                "body": {
                  "mode": "raw",
                  "raw": "{\n    \"parkingAssetIds\": [\n        \"<string>\",\n        \"<string>\"\n    ]\n}"
                }
              },
              "status": "OK",
              "code": 200,
              "header": [
                {
                  "key": "Content-Type",
                  "value": "application/json"
                }
              ],
              "body": "{\n \"success\": true,\n \"result\": [\n  {\n   \"id\": \"reprehenderit\",\n   \"name\": \"exercitation deserunt ve\"\n  },\n  {\n   \"id\": \"ex tempor et\",\n   \"name\": \"laboris\"\n  }\n ]\n}",
              "cookie": [],
              "_postman_previewlanguage": "json"
            },
            {
              "id": "aba5a814-4815-4621-bda9-669422468114",
              "name": "Bad Request",
              "originalRequest": {
                "url": {
                  "path": [
                    "queries",
                    "getParkingAssetHeaders"
                  ],
                  "host": [
                    "{{baseUrl}}"
                  ],
                  "query": [],
                  "variable": []
                },
                "method": "POST",
                "body": {
                  "mode": "raw",
                  "raw": "{\n    \"parkingAssetIds\": [\n        \"<string>\",\n        \"<string>\"\n    ]\n}"
                }
              },
              "status": "Bad Request",
              "code": 400,
              "header": [
                {
                  "key": "Content-Type",
                  "value": "application/json"
                }
              ],
              "body": "{\n \"success\": false,\n \"message\": \"et non ut elit\",\n \"errors\": [\n  {\n   \"property\": \"Lorem eiusmod\",\n   \"code\": \"enim non\",\n   \"message\": \"ad in\"\n  },\n  {\n   \"property\": \"sit ullamco nulla\",\n   \"code\": \"esse proident cupidatat Lorem nulla\",\n   \"message\": \"velit et nisi sint\"\n  }\n ]\n}",
              "cookie": [],
              "_postman_previewlanguage": "json"
            },
            {
              "id": "4cc0f385-6e36-48b9-b725-47ffa85065d0",
              "name": "Unauthorized",
              "originalRequest": {
                "url": {
                  "path": [
                    "queries",
                    "getParkingAssetHeaders"
                  ],
                  "host": [
                    "{{baseUrl}}"
                  ],
                  "query": [],
                  "variable": []
                },
                "method": "POST",
                "body": {
                  "mode": "raw",
                  "raw": "{\n    \"parkingAssetIds\": [\n        \"<string>\",\n        \"<string>\"\n    ]\n}"
                }
              },
              "status": "Unauthorized",
              "code": 401,
              "header": [
                {
                  "key": "Content-Type",
                  "value": "text/plain"
                }
              ],
              "body": "",
              "cookie": [],
              "_postman_previewlanguage": "text"
            },
            {
              "id": "29aaafb7-8e6c-4129-b5b8-1eeb9aed0a46",
              "name": "Forbidden",
              "originalRequest": {
                "url": {
                  "path": [
                    "queries",
                    "getParkingAssetHeaders"
                  ],
                  "host": [
                    "{{baseUrl}}"
                  ],
                  "query": [],
                  "variable": []
                },
                "method": "POST",
                "body": {
                  "mode": "raw",
                  "raw": "{\n    \"parkingAssetIds\": [\n        \"<string>\",\n        \"<string>\"\n    ]\n}"
                }
              },
              "status": "Forbidden",
              "code": 403,
              "header": [
                {
                  "key": "Content-Type",
                  "value": "text/plain"
                }
              ],
              "body": "",
              "cookie": [],
              "_postman_previewlanguage": "text"
            },
            {
              "id": "2f54edc2-8ca4-4690-86b6-17c04aba9ea5",
              "name": "Too many requests",
              "originalRequest": {
                "url": {
                  "path": [
                    "queries",
                    "getParkingAssetHeaders"
                  ],
                  "host": [
                    "{{baseUrl}}"
                  ],
                  "query": [],
                  "variable": []
                },
                "method": "POST",
                "body": {
                  "mode": "raw",
                  "raw": "{\n    \"parkingAssetIds\": [\n        \"<string>\",\n        \"<string>\"\n    ]\n}"
                }
              },
              "status": "Too Many Requests",
              "code": 429,
              "header": [
                {
                  "key": "Content-Type",
                  "value": "text/plain"
                }
              ],
              "body": "",
              "cookie": [],
              "_postman_previewlanguage": "text"
            }
          ],
          "event": []
        },
        {
          "id": "69f69420-4cfa-4813-b425-44559a92066f",
          "name": "/queries/getRecentlyOccupiedBays - POST",
          "request": {
            "name": "/queries/getRecentlyOccupiedBays - POST",
            "description": {},
            "url": {
              "path": [
                "queries",
                "getRecentlyOccupiedBays"
              ],
              "host": [
                "{{baseUrl}}"
              ],
              "query": [],
              "variable": []
            },
            "header": [
              {
                "key": "Content-Type",
                "value": "application/json"
              }
            ],
            "method": "POST",
            "auth": null,
            "body": {
              "mode": "raw",
              "raw": "{\n    \"parkingAssetId\": \"<string>\"\n}"
            }
          },
          "response": [
            {
              "id": "d59bc8ef-49f6-4801-a748-98667e873408",
              "name": "Success",
              "originalRequest": {
                "url": {
                  "path": [
                    "queries",
                    "getRecentlyOccupiedBays"
                  ],
                  "host": [
                    "{{baseUrl}}"
                  ],
                  "query": [],
                  "variable": []
                },
                "method": "POST",
                "body": {
                  "mode": "raw",
                  "raw": "{\n    \"parkingAssetId\": \"<string>\"\n}"
                }
              },
              "status": "OK",
              "code": 200,
              "header": [
                {
                  "key": "Content-Type",
                  "value": "application/json"
                }
              ],
              "body": "{\n \"success\": false,\n \"result\": [\n  {\n   \"bayId\": \"quis Ut minim laboris do\",\n   \"occupancySessionId\": \"cupidatat aliquip commodo\",\n   \"occupancyStartTimeUtc\": \"nulla ex dolore\"\n  },\n  {\n   \"bayId\": \"tempor sunt\",\n   \"occupancySessionId\": \"velit Ut e\",\n   \"occupancyStartTimeUtc\": \"c\"\n  }\n ]\n}",
              "cookie": [],
              "_postman_previewlanguage": "json"
            },
            {
              "id": "9087bb2c-c16c-4bf9-a881-3e55705da291",
              "name": "Bad Request",
              "originalRequest": {
                "url": {
                  "path": [
                    "queries",
                    "getRecentlyOccupiedBays"
                  ],
                  "host": [
                    "{{baseUrl}}"
                  ],
                  "query": [],
                  "variable": []
                },
                "method": "POST",
                "body": {
                  "mode": "raw",
                  "raw": "{\n    \"parkingAssetId\": \"<string>\"\n}"
                }
              },
              "status": "Bad Request",
              "code": 400,
              "header": [
                {
                  "key": "Content-Type",
                  "value": "application/json"
                }
              ],
              "body": "{\n \"success\": false,\n \"message\": \"et non ut elit\",\n \"errors\": [\n  {\n   \"property\": \"Lorem eiusmod\",\n   \"code\": \"enim non\",\n   \"message\": \"ad in\"\n  },\n  {\n   \"property\": \"sit ullamco nulla\",\n   \"code\": \"esse proident cupidatat Lorem nulla\",\n   \"message\": \"velit et nisi sint\"\n  }\n ]\n}",
              "cookie": [],
              "_postman_previewlanguage": "json"
            },
            {
              "id": "1f179424-b97a-41c3-9560-e74e8abd7bab",
              "name": "Unauthorized",
              "originalRequest": {
                "url": {
                  "path": [
                    "queries",
                    "getRecentlyOccupiedBays"
                  ],
                  "host": [
                    "{{baseUrl}}"
                  ],
                  "query": [],
                  "variable": []
                },
                "method": "POST",
                "body": {
                  "mode": "raw",
                  "raw": "{\n    \"parkingAssetId\": \"<string>\"\n}"
                }
              },
              "status": "Unauthorized",
              "code": 401,
              "header": [
                {
                  "key": "Content-Type",
                  "value": "text/plain"
                }
              ],
              "body": "",
              "cookie": [],
              "_postman_previewlanguage": "text"
            },
            {
              "id": "d0b65568-cde9-4e63-9773-f3b1c047de6e",
              "name": "Forbidden",
              "originalRequest": {
                "url": {
                  "path": [
                    "queries",
                    "getRecentlyOccupiedBays"
                  ],
                  "host": [
                    "{{baseUrl}}"
                  ],
                  "query": [],
                  "variable": []
                },
                "method": "POST",
                "body": {
                  "mode": "raw",
                  "raw": "{\n    \"parkingAssetId\": \"<string>\"\n}"
                }
              },
              "status": "Forbidden",
              "code": 403,
              "header": [
                {
                  "key": "Content-Type",
                  "value": "text/plain"
                }
              ],
              "body": "",
              "cookie": [],
              "_postman_previewlanguage": "text"
            },
            {
              "id": "9df6ea25-7a9d-40a2-a51d-81b5e7079d1a",
              "name": "Too many requests",
              "originalRequest": {
                "url": {
                  "path": [
                    "queries",
                    "getRecentlyOccupiedBays"
                  ],
                  "host": [
                    "{{baseUrl}}"
                  ],
                  "query": [],
                  "variable": []
                },
                "method": "POST",
                "body": {
                  "mode": "raw",
                  "raw": "{\n    \"parkingAssetId\": \"<string>\"\n}"
                }
              },
              "status": "Too Many Requests",
              "code": 429,
              "header": [
                {
                  "key": "Content-Type",
                  "value": "text/plain"
                }
              ],
              "body": "",
              "cookie": [],
              "_postman_previewlanguage": "text"
            }
          ],
          "event": []
        },
        {
          "id": "5f843a0a-1f50-402e-bde1-ef4bc91f6f24",
          "name": "/queries/getRegistration - POST",
          "request": {
            "name": "/queries/getRegistration - POST",
            "description": {},
            "url": {
              "path": [
                "queries",
                "getRegistration"
              ],
              "host": [
                "{{baseUrl}}"
              ],
              "query": [],
              "variable": []
            },
            "header": [
              {
                "key": "Content-Type",
                "value": "application/json"
              }
            ],
            "method": "POST",
            "auth": null,
            "body": {
              "mode": "raw",
              "raw": "{\n    \"id\": \"<string>\"\n}"
            }
          },
          "response": [
            {
              "id": "092823bd-e4bc-4857-a23c-e02f77023ab3",
              "name": "Success",
              "originalRequest": {
                "url": {
                  "path": [
                    "queries",
                    "getRegistration"
                  ],
                  "host": [
                    "{{baseUrl}}"
                  ],
                  "query": [],
                  "variable": []
                },
                "method": "POST",
                "body": {
                  "mode": "raw",
                  "raw": "{\n    \"id\": \"<string>\"\n}"
                }
              },
              "status": "OK",
              "code": 200,
              "header": [
                {
                  "key": "Content-Type",
                  "value": "application/json"
                }
              ],
              "body": "{\n \"success\": false,\n \"result\": {\n  \"id\": \"Ut Lorem\",\n  \"parkingAssetId\": \"mollit et\",\n  \"bayId\": \"exercitation proident anim voluptate\",\n  \"createdOnUtc\": \"enim culpa anim sit nostrud\",\n  \"startUtc\": \"ea laborum qui aliquip\",\n  \"endUtc\": \"et enim\",\n  \"vehicleRegistrationMark\": \"ut consectetur eu\",\n  \"fullName\": \"Lorem pariatur commodo\",\n  \"visitedName\": \"nostrud do nulla\",\n  \"occupancySessionId\": \"nostrud in\"\n }\n}",
              "cookie": [],
              "_postman_previewlanguage": "json"
            },
            {
              "id": "ce3f8e3f-132b-4948-b913-b39510dd976f",
              "name": "Bad Request",
              "originalRequest": {
                "url": {
                  "path": [
                    "queries",
                    "getRegistration"
                  ],
                  "host": [
                    "{{baseUrl}}"
                  ],
                  "query": [],
                  "variable": []
                },
                "method": "POST",
                "body": {
                  "mode": "raw",
                  "raw": "{\n    \"id\": \"<string>\"\n}"
                }
              },
              "status": "Bad Request",
              "code": 400,
              "header": [
                {
                  "key": "Content-Type",
                  "value": "application/json"
                }
              ],
              "body": "{\n \"success\": false,\n \"message\": \"et non ut elit\",\n \"errors\": [\n  {\n   \"property\": \"Lorem eiusmod\",\n   \"code\": \"enim non\",\n   \"message\": \"ad in\"\n  },\n  {\n   \"property\": \"sit ullamco nulla\",\n   \"code\": \"esse proident cupidatat Lorem nulla\",\n   \"message\": \"velit et nisi sint\"\n  }\n ]\n}",
              "cookie": [],
              "_postman_previewlanguage": "json"
            },
            {
              "id": "67d3d94f-7f85-4d8a-bf69-b62955a5ba72",
              "name": "Unauthorized",
              "originalRequest": {
                "url": {
                  "path": [
                    "queries",
                    "getRegistration"
                  ],
                  "host": [
                    "{{baseUrl}}"
                  ],
                  "query": [],
                  "variable": []
                },
                "method": "POST",
                "body": {
                  "mode": "raw",
                  "raw": "{\n    \"id\": \"<string>\"\n}"
                }
              },
              "status": "Unauthorized",
              "code": 401,
              "header": [
                {
                  "key": "Content-Type",
                  "value": "text/plain"
                }
              ],
              "body": "",
              "cookie": [],
              "_postman_previewlanguage": "text"
            },
            {
              "id": "fad17cd3-fdef-441d-a634-2da7a0363120",
              "name": "Forbidden",
              "originalRequest": {
                "url": {
                  "path": [
                    "queries",
                    "getRegistration"
                  ],
                  "host": [
                    "{{baseUrl}}"
                  ],
                  "query": [],
                  "variable": []
                },
                "method": "POST",
                "body": {
                  "mode": "raw",
                  "raw": "{\n    \"id\": \"<string>\"\n}"
                }
              },
              "status": "Forbidden",
              "code": 403,
              "header": [
                {
                  "key": "Content-Type",
                  "value": "text/plain"
                }
              ],
              "body": "",
              "cookie": [],
              "_postman_previewlanguage": "text"
            },
            {
              "id": "6a7ebf71-58be-42bf-b7a9-d651a2453479",
              "name": "Too many requests",
              "originalRequest": {
                "url": {
                  "path": [
                    "queries",
                    "getRegistration"
                  ],
                  "host": [
                    "{{baseUrl}}"
                  ],
                  "query": [],
                  "variable": []
                },
                "method": "POST",
                "body": {
                  "mode": "raw",
                  "raw": "{\n    \"id\": \"<string>\"\n}"
                }
              },
              "status": "Too Many Requests",
              "code": 429,
              "header": [
                {
                  "key": "Content-Type",
                  "value": "text/plain"
                }
              ],
              "body": "",
              "cookie": [],
              "_postman_previewlanguage": "text"
            }
          ],
          "event": []
        }
      ],
      "event": []
    }
  ],
  "event": [],
  "variable": [
    {
      "id": "baseUrl",
      "type": "string",
      "value": "https://api.appyway.com/v1/occupancy-authentication"
    }
  ],
  "auth": {
    "type": "apikey",
    "apikey": [
      {
        "key": "value",
        "type": "string",
        "value": "{{API-KEY-LIVE}}"
      },
      {
        "key": "key",
        "type": "string",
        "value": "API-KEY"
      }
    ]
  },
  "info": {
    "_postman_id": "30748119-a0fb-43e5-8348-0330b49e3fc9",
    "name": "Occupancy Authentication API (v1.0|LIVE|Public)",
    "schema": "https://schema.getpostman.com/json/collection/v2.1.0/collection.json",
    "description": {
      "content": "",
      "type": "text/plain"
    }
  }
}
